{"codigo":1,"codigo_alumno":1,"año_academico":2025,"estado":"Activa","importe":420.5}
{"codigo":2,"codigo_alumno":2,"año_academico":2024,"estado":"Activa","importe":420.5}
{"codigo":3,"codigo_alumno":3,"año_academico":2025,"estado":"Pendiente","importe":390.0}
{"codigo":4,"codigo_alumno":4,"año_academico":2024,"estado":"Anulada","importe":0.0}
{"codigo":5,"codigo_alumno":5,"año_academico":2025,"estado":"Activa","importe":420.5}
{"codigo":6,"codigo_alumno":6,"año_academico":2024,"estado":"Activa","importe":420.5}
{"codigo":7,"codigo_alumno":7,"año_academico":2025,"estado":"Activa","importe":420.5}
{"codigo":8,"codigo_alumno":8,"año_academico":2024,"estado":"Activa","importe":420.5}
