{"codigo":1,"codigo_ciclo":1,"nombre":"Programación","curso":"1","creditos_ects":14.0,"horas":256}
{"codigo":2,"codigo_ciclo":9,"nombre":"Bases de Datos","curso":"1","creditos_ects":11.0,"horas":192}
{"codigo":3,"codigo_ciclo":1,"nombre":"Lenguajes de Marcas","curso":"1","creditos_ects":7.0,"horas":128}
{"codigo":4,"codigo_ciclo":9,"nombre":"Acceso a Datos","curso":"2","creditos_ects":9.0,"horas":120}
{"codigo":5,"codigo_ciclo":1,"nombre":"Desarrollo de Interfaces","curso":"2","creditos_ects":9.0,"horas":120}
{"codigo":6,"codigo_ciclo":9,"nombre":"Implantación de Sistemas Operativos","curso":"1","creditos_ects":12.0,"horas":224}
{"codigo":7,"codigo_ciclo":2,"nombre":"Redes Locales","curso":"1","creditos_ects":11.0,"horas":192}
{"codigo":8,"codigo_ciclo":2,"nombre":"Seguridad y Alta Disponibilidad","curso":"2","creditos_ects":6.0,"horas":100}
{"codigo":9,"codigo_ciclo":9,"nombre":"Comunicación Empresarial","curso":"1","creditos_ects":13.66,"horas":160}
{"codigo":10,"codigo_ciclo":3,"nombre":"Operaciones Administrativas","curso":"1","creditos_ects":12.4,"horas":190}
{"codigo":11,"codigo_ciclo":9,"nombre":"asdad","curso":"1","creditos_ects":2.0,"horas":2}
{"codigo":12,"codigo_ciclo":1,"nombre":"Prueba 8","curso":"1","creditos_ects":10.0,"horas":2000}
